dnsgen/__init__.py
dnsgen/cli.py
dnsgen/dnsgen.py
dnsgen/words.txt
dnsgen-1.0.4.dist-info/LICENSE
dnsgen-1.0.4.dist-info/METADATA
dnsgen-1.0.4.dist-info/WHEEL
dnsgen-1.0.4.dist-info/entry_points.txt
dnsgen-1.0.4.dist-info/top_level.txt
dnsgen-1.0.4.dist-info/RECORD
