Metadata-Version: 2.1
Name: dnsgen
Version: 1.0.4
Summary: Generates DNS possibilities from existing domain names.
Home-page: https://github.com/me/myproject
Author: Patrik Hudak
Author-email: pato.hudak@gmail.com
License: MIT
Platform: UNKNOWN
Classifier: License :: OSI Approved :: MIT License
Classifier: Programming Language :: Python
Classifier: Programming Language :: Python :: 3
Classifier: Programming Language :: Python :: 3.6
Classifier: Programming Language :: Python :: Implementation :: CPython
Classifier: Programming Language :: Python :: Implementation :: PyPy
Requires-Python: >=3.6.0
Requires-Dist: Click
Requires-Dist: tldextract
